wsgi_microservice_middleware/__init__.py
wsgi_microservice_middleware/cors.py
wsgi_microservice_middleware/request_id.py
wsgi_microservice_middleware-0.1.6.dist-info/METADATA
wsgi_microservice_middleware-0.1.6.dist-info/WHEEL
wsgi_microservice_middleware-0.1.6.dist-info/top_level.txt
wsgi_microservice_middleware-0.1.6.dist-info/RECORD
