Metadata-Version: 2.1
Name: wsgi-microservice-middleware
Version: 0.1.6
Summary: WSGI Microservice Middleware
Home-page: https://github.com/presalytics/WSGI-Microservice-Middleware
Author-email: inquiries@presalytics.io
License: MIT
Project-URL: Issues, https://github.com/presalytics/WSGI-Microservice-Middleware/issues
Keywords: WSGI,middleware,microservice
Platform: UNKNOWN
Classifier: Programming Language :: Python :: 3
Classifier: License :: OSI Approved :: MIT License
Classifier: Operating System :: OS Independent
Classifier: Programming Language :: Python :: 3.5
Classifier: Programming Language :: Python :: 3.6
Classifier: Programming Language :: Python :: 3.7
Classifier: Programming Language :: Python :: 3.8
Classifier: Topic :: Internet :: WWW/HTTP :: WSGI :: Middleware
Classifier: Natural Language :: English
Classifier: Development Status :: 4 - Beta
Requires-Python: >=3.5
Requires-Dist: urllib3 (>=1.15)
Requires-Dist: environs (>=4.2.0)
Requires-Dist: python-json-logger (>=0.1.11)
